biosero_data_services_sdk/__init__.py
biosero_data_services_sdk/constants.py
biosero_data_services_sdk/events_sdk.py
biosero_data_services_sdk/exceptions.py
biosero_data_services_sdk/identities_sdk.py
biosero_data_services_sdk/locations_sdk.py
biosero_data_services_sdk/orders_sdk.py
biosero_data_services_sdk/py.typed
biosero_data_services_sdk/reports.py
biosero_data_services_sdk/sdk.py
biosero_data_services_sdk/sdk_base.py
biosero_data_services_sdk/transportation_sdk.py
biosero_data_services_sdk/types.py
biosero_data_services_sdk/models/__init__.py
biosero_data_services_sdk/models/base.py
biosero_data_services_sdk/models/container.py
biosero_data_services_sdk/models/event.py
biosero_data_services_sdk/models/identity.py
biosero_data_services_sdk/models/order.py
biosero_data_services_sdk/models/order_template.py
biosero_data_services_sdk/models/transportation.py
biosero_data_services_sdk-0.4.9.dist-info/METADATA
biosero_data_services_sdk-0.4.9.dist-info/WHEEL
biosero_data_services_sdk-0.4.9.dist-info/top_level.txt
biosero_data_services_sdk-0.4.9.dist-info/RECORD
