Metadata-Version: 2.4
Name: biosero-data-services-sdk
Version: 0.4.9
Summary: SDK for interacting with the Biosero Data Services API
Author: Eli Fine
Classifier: Programming Language :: Python :: 3
Classifier: Programming Language :: Python :: 3.12
Classifier: Programming Language :: Python :: 3.13
Requires-Python: >=3.12.7
Requires-Dist: pydantic>=2.12.2
Requires-Dist: nested-diff>=1.8.0
Requires-Dist: requests>=2.32.4
